pyannote.db.repere-0.2.dist-info/DESCRIPTION.rst
pyannote.db.repere-0.2.dist-info/entry_points.txt
pyannote.db.repere-0.2.dist-info/METADATA
pyannote.db.repere-0.2.dist-info/metadata.json
pyannote.db.repere-0.2.dist-info/RECORD
pyannote.db.repere-0.2.dist-info/top_level.txt
pyannote.db.repere-0.2.dist-info/WHEEL
REPERE/__init__.py
REPERE/_version.py
REPERE/data/speaker/all.trn.lst
REPERE/data/speaker/all.trn.mdtm
REPERE/data/speaker/all.trn.uem
REPERE/data/speaker/dryrun.dev.lst
REPERE/data/speaker/dryrun.dev.mdtm
REPERE/data/speaker/dryrun.dev.uem
REPERE/data/speaker/dryrun.tst.lst
REPERE/data/speaker/dryrun.tst.mdtm
REPERE/data/speaker/dryrun.tst.uem
REPERE/data/speaker/phase1.dev.lst
REPERE/data/speaker/phase1.dev.mdtm
REPERE/data/speaker/phase1.dev.uem
REPERE/data/speaker/phase1.trn.lst
REPERE/data/speaker/phase1.trn.mdtm
REPERE/data/speaker/phase1.trn.uem
REPERE/data/speaker/phase1.tst.lst
REPERE/data/speaker/phase1.tst.mdtm
REPERE/data/speaker/phase1.tst.uem
REPERE/data/speaker/phase2.dev.lst
REPERE/data/speaker/phase2.dev.mdtm
REPERE/data/speaker/phase2.dev.uem
REPERE/data/speaker/phase2.trn.lst
REPERE/data/speaker/phase2.trn.mdtm
REPERE/data/speaker/phase2.trn.uem
REPERE/data/speaker/phase2.tst.lst
REPERE/data/speaker/phase2.tst.mdtm
REPERE/data/speaker/phase2.tst.uem
